tka/__init__.py
tka/data/__init__.py
tka/data/assay_metadata.csv
tka/data/auc_modalities_(2021-02-mobc-es-op).csv
tka/data/auc_modalities_(2023-01-mobc-es-op).csv
tka/data/auc_modalities_(2023-02-mobc-es-op).csv
tka/data/auc_modalities_(2024-01-mobc-es-op).csv
tka/data/feature_means.csv
tka/data/l1000_mapped.csv
tka/data/mobc_feature_columns_(2021-02-mobc-es-op).txt
tka/data/mobc_feature_columns_(2023-01-mobc-es-op).txt
tka/data/mobc_feature_columns_(2023-02-mobc-es-op).txt
tka/data/mobc_feature_columns_(2024-01-mobc-es-op).txt
tka/docs/Makefile
tka/docs/__init__.py
tka/docs/_build/doctrees/documentation.doctree
tka/docs/_build/doctrees/environment.pickle
tka/docs/_build/doctrees/external_models.doctree
tka/docs/_build/doctrees/external_models.moshkov.doctree
tka/docs/_build/doctrees/index.doctree
tka/docs/_build/doctrees/installation.doctree
tka/docs/_build/doctrees/metrics.doctree
tka/docs/_build/doctrees/metrics.signatures.doctree
tka/docs/_build/doctrees/overview.doctree
tka/docs/_build/doctrees/utils.doctree
tka/docs/_build/html/.buildinfo
tka/docs/_build/html/_modules/index.html
tka/docs/_build/html/_modules/tka/external_models/moshkov.html
tka/docs/_build/html/_modules/tka/metrics/signatures.html
tka/docs/_build/html/_modules/tka/utils.html
tka/docs/_build/html/_sources/documentation.rst.txt
tka/docs/_build/html/_sources/external_models.moshkov.rst.txt
tka/docs/_build/html/_sources/external_models.rst.txt
tka/docs/_build/html/_sources/index.rst.txt
tka/docs/_build/html/_sources/installation.rst.txt
tka/docs/_build/html/_sources/metrics.rst.txt
tka/docs/_build/html/_sources/metrics.signatures.rst.txt
tka/docs/_build/html/_sources/overview.rst.txt
tka/docs/_build/html/_sources/utils.rst.txt
tka/docs/_build/html/_static/_sphinx_javascript_frameworks_compat.js
tka/docs/_build/html/_static/basic.css
tka/docs/_build/html/_static/css/badge_only.css
tka/docs/_build/html/_static/css/fonts/Roboto-Slab-Bold.woff
tka-0.6.4.dist-info/LICENSE
tka-0.6.4.dist-info/METADATA
tka-0.6.4.dist-info/WHEEL
tka-0.6.4.dist-info/RECORD
